tests/__init__.py
tests/test_gdc.py
tests/test_gdc2xena.py
tests/test_main.py
tests/test_utils.py
tests/test_xena_dataset.py
xena_gdc_etl/__init__.py
xena_gdc_etl/constants.py
xena_gdc_etl/gdc.py
xena_gdc_etl/gdc2xena.py
xena_gdc_etl/main.py
xena_gdc_etl/utils.py
xena_gdc_etl/xena_dataset.py
xena_gdc_etl/resources/gencode-v22_to_probeMap.sh
xena_gdc_etl/resources/gencode.v22.annotation.gene.probeMap
xena_gdc_etl/resources/gencode.v22.annotation.gene.probeMap.json
xena_gdc_etl/resources/illuminaMethyl27_hg38_GDC
xena_gdc_etl/resources/illuminaMethyl27_hg38_GDC.json
xena_gdc_etl/resources/illuminaMethyl450_hg38_GDC
xena_gdc_etl/resources/illuminaMethyl450_hg38_GDC.json
xena_gdc_etl/resources/template.api_phenotype.meta.json
xena_gdc_etl/resources/template.cnv.meta.json
xena_gdc_etl/resources/template.gistic.meta.json
xena_gdc_etl/resources/template.methylation.meta.json
xena_gdc_etl/resources/template.mirna.meta.json
xena_gdc_etl/resources/template.mirna_isoform.meta.json
xena_gdc_etl/resources/template.phenotype.meta.json
xena_gdc_etl/resources/template.rna.meta.json
xena_gdc_etl/resources/template.snv.meta.json
xena_gdc_etl/resources/template.survival.meta.json
xena_gdc_etl-0.2.0.data/scripts/TARGET-CCSK_phenotype_ETL.py
xena_gdc_etl-0.2.0.data/scripts/join_xena.sh
xena_gdc_etl-0.2.0.data/scripts/panTCGA.py
xena_gdc_etl-0.2.0.data/scripts/union_xena.sh
xena_gdc_etl-0.2.0.dist-info/LICENSE
xena_gdc_etl-0.2.0.dist-info/METADATA
xena_gdc_etl-0.2.0.dist-info/WHEEL
xena_gdc_etl-0.2.0.dist-info/entry_points.txt
xena_gdc_etl-0.2.0.dist-info/top_level.txt
xena_gdc_etl-0.2.0.dist-info/RECORD
