Metadata-Version: 2.1
Name: xena-gdc-etl
Version: 0.2.0
Summary: Scripts for importing GDC data into UCSC Xena.
Home-page: https://github.com/yunhailuo/xena-GDC-ETL
Author: Yunhai Luo
Author-email: yunhail@stanford.edu
License: Apache License 2.0
Keywords: Xena Genomic Data Commons GDC
Platform: UNKNOWN
Classifier: Programming Language :: Python :: 2.7
Classifier: Programming Language :: Python :: 3.5
Classifier: Programming Language :: Python :: 3.6
Classifier: Programming Language :: Python :: 3.7
Classifier: License :: OSI Approved :: Apache Software License
Classifier: Operating System :: OS Independent
Requires-Dist: jinja2 (>=2.10.1)
Requires-Dist: lxml (>=4.2.0)
Requires-Dist: numpy (>=1.15.0)
Requires-Dist: pandas (>=0.23.2)
Requires-Dist: requests (>=2.20.0)
Requires-Dist: xlrd (>=1.1.0)
Requires-Dist: mock (>=2.0.0)
